LICENSE
MANIFEST.in
README.md
pyproject.toml
setup.py
pyPhasesRecordloader/Event.py
pyPhasesRecordloader/EventManager.py
pyPhasesRecordloader/NormalizeRecordSignal.py
pyPhasesRecordloader/Plugin.py
pyPhasesRecordloader/RecordLoader.py
pyPhasesRecordloader/RecordSignal.py
pyPhasesRecordloader/Signal.py
pyPhasesRecordloader/SignalPreprocessing.py
pyPhasesRecordloader/__init__.py
pyPhasesRecordloader.egg-info/PKG-INFO
pyPhasesRecordloader.egg-info/SOURCES.txt
pyPhasesRecordloader.egg-info/dependency_links.txt
pyPhasesRecordloader.egg-info/requires.txt
pyPhasesRecordloader.egg-info/top_level.txt
pyPhasesRecordloader/downloader/Downloader.py
pyPhasesRecordloader/downloader/FolderDownloader.py
pyPhasesRecordloader/downloader/HTMLDownloader.py
pyPhasesRecordloader/downloader/ListDownloader.py
pyPhasesRecordloader/downloader/NSRRDownloader.py
pyPhasesRecordloader/downloader/S3Downloader.py
pyPhasesRecordloader/downloader/__init__.py
pyPhasesRecordloader/recordLoaders/CSVMetaLoader.py
pyPhasesRecordloader/recordLoaders/EDFRecordLoader.py
pyPhasesRecordloader/recordLoaders/H5RecordLoader.py
pyPhasesRecordloader/recordLoaders/MatRecordLoader.py
pyPhasesRecordloader/recordLoaders/MultiSegmentEDFRecordLoader.py
pyPhasesRecordloader/recordLoaders/WFDBRecordLoader.py
pyPhasesRecordloader/recordLoaders/XMLAnnotationLoader.py
pyPhasesRecordloader/recordLoaders/__init__.py
pyPhasesRecordloader/util/DynamicModule.py
pyPhasesRecordloader/util/__init__.py