Metadata-Version: 2.4
Name: pyPhasesRecordloader
Version: 0.11.5
Summary: Adds a record loaders to the pyPhases package
Home-page: https://gitlab.com/tud.ibmt.public/pyphases/pyphasesrecordloader/
Author: Franz Ehrlich
Author-email: fehrlichd@gmail.com
Classifier: Programming Language :: Python :: 3
Classifier: License :: OSI Approved :: MIT License
Classifier: Operating System :: OS Independent
Requires-Python: >=3.5
License-File: LICENSE
Requires-Dist: pyPhases
Requires-Dist: numpy
Requires-Dist: tqdm
Requires-Dist: pandas
Dynamic: author
Dynamic: author-email
Dynamic: classifier
Dynamic: description
Dynamic: description-content-type
Dynamic: home-page
Dynamic: license-file
Dynamic: requires-dist
Dynamic: requires-python
Dynamic: summary
